trustcv/__init__.py
trustcv/validators.py
trustcv/checkers/__init__.py
trustcv/checkers/balance.py
trustcv/checkers/leakage.py
trustcv/core/__init__.py
trustcv/core/base.py
trustcv/core/callbacks.py
trustcv/core/runner.py
trustcv/datasets/__init__.py
trustcv/datasets/loaders.py
trustcv/frameworks/__init__.py
trustcv/frameworks/jax.py
trustcv/frameworks/monai.py
trustcv/frameworks/pytorch.py
trustcv/frameworks/tensorflow.py
trustcv/metrics/__init__.py
trustcv/metrics/clinical.py
trustcv/metrics/medical_metrics.py
trustcv/reporting/__init__.py
trustcv/reporting/regulatory_report.py
trustcv/reporting/universal_report.py
trustcv/splitters/__init__.py
trustcv/splitters/grouped.py
trustcv/splitters/iid.py
trustcv/splitters/spatial.py
trustcv/splitters/temporal.py
trustcv/visualization/__init__.py
trustcv/visualization/plots.py
trustcv-1.0.5.dist-info/licenses/AUTHORS.md
trustcv-1.0.5.dist-info/licenses/LICENSE
trustcv-1.0.5.dist-info/METADATA
trustcv-1.0.5.dist-info/WHEEL
trustcv-1.0.5.dist-info/top_level.txt
trustcv-1.0.5.dist-info/RECORD
