Metadata-Version: 2.4
Name: trustcv
Version: 1.0.5
Summary: Trustworthy Cross-Validation: Framework-agnostic CV with data leakage detection
Home-page: https://github.com/ki-smile/trustcv
Author: SMAILE (Stockholm Medical AI and Learning Environments), Karolinska Institutet
Project-URL: SMAILE Lab, https://smile.ki.se
Project-URL: Documentation, https://ki-smile.github.io/trustcv
Project-URL: Bug Tracker, https://github.com/ki-smile/trustcv/issues
Keywords: machine learning,cross-validation,AI,healthcare,clinical research,regulatory compliance,FDA,CE MDR,pytorch,tensorflow,MONAI,framework-agnostic
Classifier: Development Status :: 5 - Production/Stable
Classifier: Intended Audience :: Healthcare Industry
Classifier: Intended Audience :: Science/Research
Classifier: Intended Audience :: Developers
Classifier: Topic :: Scientific/Engineering :: Medical Science Apps.
Classifier: Topic :: Scientific/Engineering :: Artificial Intelligence
Classifier: Topic :: Scientific/Engineering :: Bio-Informatics
Classifier: License :: OSI Approved :: MIT License
Classifier: Programming Language :: Python :: 3
Classifier: Programming Language :: Python :: 3.8
Classifier: Programming Language :: Python :: 3.9
Classifier: Programming Language :: Python :: 3.10
Classifier: Programming Language :: Python :: 3.11
Classifier: Operating System :: OS Independent
Requires-Python: >=3.8
License-File: LICENSE
License-File: AUTHORS.md
Requires-Dist: numpy>=1.20.0
Requires-Dist: pandas>=1.3.0
Requires-Dist: scikit-learn>=1.0.0
Requires-Dist: matplotlib>=3.4.0
Requires-Dist: seaborn>=0.11.0
Requires-Dist: scipy>=1.7.0
Requires-Dist: plotly>=5.0.0
Requires-Dist: joblib>=1.0.0
Requires-Dist: tqdm>=4.60.0
Provides-Extra: pytorch
Requires-Dist: torch>=1.10.0; extra == "pytorch"
Requires-Dist: torchvision>=0.11.0; extra == "pytorch"
Provides-Extra: tensorflow
Requires-Dist: tensorflow>=2.10.0; extra == "tensorflow"
Provides-Extra: monai
Requires-Dist: monai>=1.0.0; extra == "monai"
Requires-Dist: nibabel>=3.2.0; extra == "monai"
Requires-Dist: torch>=1.10.0; extra == "monai"
Provides-Extra: jax
Requires-Dist: jax>=0.4.0; extra == "jax"
Requires-Dist: jaxlib>=0.4.0; extra == "jax"
Requires-Dist: flax>=0.6.0; extra == "jax"
Provides-Extra: xgboost
Requires-Dist: xgboost>=1.7.0; extra == "xgboost"
Provides-Extra: lightgbm
Requires-Dist: lightgbm>=3.3.0; extra == "lightgbm"
Provides-Extra: catboost
Requires-Dist: catboost>=1.1.0; extra == "catboost"
Provides-Extra: all
Requires-Dist: torch>=1.10.0; extra == "all"
Requires-Dist: torchvision>=0.11.0; extra == "all"
Requires-Dist: tensorflow>=2.10.0; extra == "all"
Requires-Dist: monai>=1.0.0; extra == "all"
Requires-Dist: nibabel>=3.2.0; extra == "all"
Requires-Dist: xgboost>=1.7.0; extra == "all"
Requires-Dist: lightgbm>=3.3.0; extra == "all"
Requires-Dist: optuna>=3.0.0; extra == "all"
Provides-Extra: dev
Requires-Dist: pytest>=6.0; extra == "dev"
Requires-Dist: pytest-cov>=2.0; extra == "dev"
Requires-Dist: black>=21.0; extra == "dev"
Requires-Dist: flake8>=3.9; extra == "dev"
Requires-Dist: mypy>=0.900; extra == "dev"
Requires-Dist: isort>=5.10.0; extra == "dev"
Provides-Extra: docs
Requires-Dist: sphinx>=4.0; extra == "docs"
Requires-Dist: sphinx-rtd-theme>=0.5; extra == "docs"
Requires-Dist: sphinx-autodoc-typehints>=1.12.0; extra == "docs"
Requires-Dist: myst-parser>=0.18.0; extra == "docs"
Dynamic: author
Dynamic: classifier
Dynamic: description
Dynamic: description-content-type
Dynamic: home-page
Dynamic: keywords
Dynamic: license-file
Dynamic: project-url
Dynamic: provides-extra
Dynamic: requires-dist
Dynamic: requires-python
Dynamic: summary
